{
	"$schema": "http://schema.management.azure.com/schemas/2015-01-01/deploymentTemplate.json#",
	"contentVersion": "1.0.0.0",
	"parameters": {
		"factoryName": {
			"type": "string",
			"metadata": "Data Factory name",
			"defaultValue": "db-data-archiving"
		}
	},
	"variables": {
		"factoryId": "[concat('Microsoft.DataFactory/factories/', parameters('factoryName'))]"
	},
	"resources": [
		{
			"name": "[concat(parameters('factoryName'), '/Delete_hcStaffCustomFields')]",
			"type": "Microsoft.DataFactory/factories/pipelines",
			"apiVersion": "2018-06-01",
			"properties": {
				"activities": [
					{
						"name": "Script1",
						"type": "Script",
						"dependsOn": [],
						"policy": {
							"timeout": "0.12:00:00",
							"retry": 0,
							"retryIntervalInSeconds": 30,
							"secureOutput": false,
							"secureInput": false
						},
						"userProperties": [],
						"linkedServiceName": {
							"referenceName": "BHDataArchiveDev",
							"type": "LinkedServiceReference"
						},
						"typeProperties": {
							"scripts": [
								{
									"type": "Query",
									"text": {
										"value": "DELETE t\nFROM dbo.hcStaffCustomFields t\nINNER JOIN dbo.AccountInfo a ON t.accountInfoId = a.ID\nINNER JOIN dbo.Subscription sub ON sub.accountInfoID = a.ID\nINNER JOIN dbo.AccountsToDelete atd ON a.ID = atd.AccountId\n\n-- OptionValues path\nINNER JOIN dbo.hcStaffCustomFieldsOptions o ON o.StaffCustomFieldId = t.id\nINNER JOIN dbo.hcStaffCustomFieldOptionValues v ON v.OptionId = o.Id\nINNER JOIN dbo.tblMember tm1 ON tm1.id = v.StaffMemberId\nINNER JOIN dbo.AccountsToDelete atd1 ON tm1.accountInfoId = atd1.AccountId\n\n-- FieldValues path\nINNER JOIN dbo.hcStaffCustomFieldValues fv ON fv.StaffCustomFieldEntityId = t.id\nINNER JOIN dbo.tblMember tm2 ON tm2.id = fv.StaffMemberId\nINNER JOIN dbo.AccountsToDelete atd2 ON tm2.accountInfoId = atd2.AccountId\n/**\nWHERE\n    (\n        atd.AccountId IS NOT NULL\n        OR atd1.AccountId IS NOT NULL\n        OR atd2.AccountId IS NOT NULL\n    )\n    AND (\n        sub.OrganizationTypeId <> 2\n        OR (\n            sub.OrganizationTypeId = 2\n            AND a.ID NOT IN (23382)\n            AND sub.SubscriptionStatusID <> 1\n            AND sub.dateSubscriptionStatusChanged <= DATEADD(MONTH, -6, GETDATE())\n        )\n    );\n**/",
										"type": "Expression"
									}
								}
							],
							"scriptBlockExecutionTimeout": "02:00:00"
						}
					}
				],
				"policy": {
					"elapsedTimeMetric": {}
				},
				"annotations": [],
				"lastPublishTime": "2026-04-30T15:36:15Z"
			},
			"dependsOn": []
		},
		{
			"name": "[concat(parameters('factoryName'), '/Delete_hcStaffCustomFieldsOptions')]",
			"type": "Microsoft.DataFactory/factories/pipelines",
			"apiVersion": "2018-06-01",
			"properties": {
				"activities": [
					{
						"name": "Script1",
						"type": "Script",
						"dependsOn": [],
						"policy": {
							"timeout": "0.12:00:00",
							"retry": 0,
							"retryIntervalInSeconds": 30,
							"secureOutput": false,
							"secureInput": false
						},
						"userProperties": [],
						"linkedServiceName": {
							"referenceName": "BHDataArchiveDev",
							"type": "LinkedServiceReference"
						},
						"typeProperties": {
							"scripts": [
								{
									"type": "Query",
									"text": {
										"value": "DELETE t\nFROM dbo.hcStaffCustomFieldsOptions t\nINNER JOIN dbo.hcStaffCustomFields cf ON t.StaffCustomFieldId = cf.id\nINNER JOIN dbo.AccountInfo a ON cf.accountInfoId = a.ID\nINNER JOIN dbo.Subscription sub ON sub.accountInfoID = a.ID\nINNER JOIN dbo.AccountsToDelete atd ON a.ID = atd.AccountId\n\n-- OptionValue path\nINNER JOIN dbo.hcStaffCustomFieldOptionValues v ON v.OptionId = t.Id\nINNER JOIN dbo.tblMember tm ON tm.id = v.StaffMemberId\nINNER JOIN dbo.AccountsToDelete atd2 ON tm.accountInfoId = atd2.AccountId\n/**\nWHERE\n    (\n        atd.AccountId IS NOT NULL\n        OR atd2.AccountId IS NOT NULL\n    )\n    AND (\n        sub.OrganizationTypeId <> 2\n        OR (\n            sub.OrganizationTypeId = 2\n            AND a.ID NOT IN (23382)\n            AND sub.SubscriptionStatusID <> 1\n            AND sub.dateSubscriptionStatusChanged <= DATEADD(MONTH, -6, GETDATE())\n        )\n    );\n**/",
										"type": "Expression"
									}
								}
							],
							"scriptBlockExecutionTimeout": "02:00:00"
						}
					}
				],
				"policy": {
					"elapsedTimeMetric": {}
				},
				"annotations": [],
				"lastPublishTime": "2026-04-30T15:36:14Z"
			},
			"dependsOn": []
		},
		{
			"name": "[concat(parameters('factoryName'), '/Delete_hcStaffMember')]",
			"type": "Microsoft.DataFactory/factories/pipelines",
			"apiVersion": "2018-06-01",
			"properties": {
				"activities": [
					{
						"name": "Script1",
						"type": "Script",
						"dependsOn": [],
						"policy": {
							"timeout": "0.12:00:00",
							"retry": 0,
							"retryIntervalInSeconds": 30,
							"secureOutput": false,
							"secureInput": false
						},
						"userProperties": [],
						"linkedServiceName": {
							"referenceName": "BHDataArchiveDev",
							"type": "LinkedServiceReference"
						},
						"typeProperties": {
							"scripts": [
								{
									"type": "Query",
									"text": {
										"value": "DELETE t\nFROM dbo.hcStaffMember t\nINNER JOIN dbo.tblMember tm ON t.tblmemberid = tm.id\nINNER JOIN dbo.AccountInfo a ON tm.accountInfoId = a.ID\nINNER JOIN dbo.Subscription sub ON sub.accountInfoID = a.ID\nINNER JOIN dbo.AccountsToDelete atd ON a.ID = atd.AccountId\nWHERE t.id NOT IN (220953, 194645);  -- Exclude known bad data\n",
										"type": "Expression"
									}
								}
							],
							"scriptBlockExecutionTimeout": "02:00:00"
						}
					}
				],
				"policy": {
					"elapsedTimeMetric": {}
				},
				"annotations": [],
				"lastPublishTime": "2026-04-30T15:36:26Z"
			},
			"dependsOn": []
		},
		{
			"name": "[concat(parameters('factoryName'), '/Delete_hcStaffMemberAgeGroup')]",
			"type": "Microsoft.DataFactory/factories/pipelines",
			"apiVersion": "2018-06-01",
			"properties": {
				"activities": [
					{
						"name": "Script1",
						"type": "Script",
						"dependsOn": [],
						"policy": {
							"timeout": "0.12:00:00",
							"retry": 0,
							"retryIntervalInSeconds": 30,
							"secureOutput": false,
							"secureInput": false
						},
						"userProperties": [],
						"linkedServiceName": {
							"referenceName": "BHDataArchiveDev",
							"type": "LinkedServiceReference"
						},
						"typeProperties": {
							"scripts": [
								{
									"type": "Query",
									"text": {
										"value": "DELETE t\nFROM dbo.hcStaffMemberAgeGroup t\nINNER JOIN dbo.tblMember tm ON t.tblmemberid = tm.id\nINNER JOIN dbo.AccountInfo a ON tm.accountInfoId = a.ID\nINNER JOIN dbo.Subscription sub ON sub.accountInfoID = a.ID\nINNER JOIN dbo.AccountsToDelete atd ON a.ID = atd.AccountId\nWHERE \n    sub.OrganizationTypeId <> 2\n    OR (\n        sub.OrganizationTypeId = 2\n        AND a.ID NOT IN (23382)\n        AND sub.SubscriptionStatusID <> 1\n        AND sub.dateSubscriptionStatusChanged <= DATEADD(MONTH, -6, GETDATE())\n    );\n",
										"type": "Expression"
									}
								}
							],
							"scriptBlockExecutionTimeout": "02:00:00"
						}
					}
				],
				"policy": {
					"elapsedTimeMetric": {}
				},
				"annotations": [],
				"lastPublishTime": "2026-04-30T15:36:23Z"
			},
			"dependsOn": []
		},
		{
			"name": "[concat(parameters('factoryName'), '/Delete_hcStaffMemberCredential')]",
			"type": "Microsoft.DataFactory/factories/pipelines",
			"apiVersion": "2018-06-01",
			"properties": {
				"activities": [
					{
						"name": "Script1",
						"type": "Script",
						"dependsOn": [],
						"policy": {
							"timeout": "0.12:00:00",
							"retry": 0,
							"retryIntervalInSeconds": 30,
							"secureOutput": false,
							"secureInput": false
						},
						"userProperties": [],
						"linkedServiceName": {
							"referenceName": "BHDataArchiveDev",
							"type": "LinkedServiceReference"
						},
						"typeProperties": {
							"scripts": [
								{
									"type": "Query",
									"text": {
										"value": "DELETE t\nFROM dbo.hcStaffMemberCredential t\nINNER JOIN dbo.tblMember tm ON tm.id = t.tblmemberId\nINNER JOIN dbo.AccountInfo a ON tm.accountInfoId = a.ID\nINNER JOIN dbo.Subscription sub ON sub.accountInfoID = a.ID\nINNER JOIN dbo.AccountsToDelete atd ON a.ID = atd.AccountId\n/**WHERE \n    sub.OrganizationTypeId <> 2\n    OR (\n        sub.OrganizationTypeId = 2\n        AND a.ID NOT IN (23382)\n        AND sub.SubscriptionStatusID <> 1\n        AND sub.dateSubscriptionStatusChanged <= DATEADD(MONTH, -6, GETDATE())\n    );\n**/",
										"type": "Expression"
									}
								}
							],
							"scriptBlockExecutionTimeout": "02:00:00"
						}
					}
				],
				"policy": {
					"elapsedTimeMetric": {}
				},
				"annotations": [],
				"lastPublishTime": "2026-04-30T15:36:15Z"
			},
			"dependsOn": []
		},
		{
			"name": "[concat(parameters('factoryName'), '/Delete_hcStaffMemberLanguage')]",
			"type": "Microsoft.DataFactory/factories/pipelines",
			"apiVersion": "2018-06-01",
			"properties": {
				"activities": [
					{
						"name": "Script1",
						"type": "Script",
						"dependsOn": [],
						"policy": {
							"timeout": "0.12:00:00",
							"retry": 0,
							"retryIntervalInSeconds": 30,
							"secureOutput": false,
							"secureInput": false
						},
						"userProperties": [],
						"linkedServiceName": {
							"referenceName": "BHDataArchiveDev",
							"type": "LinkedServiceReference"
						},
						"typeProperties": {
							"scripts": [
								{
									"type": "Query",
									"text": {
										"value": "DELETE t\nFROM dbo.hcStaffMemberLanguage t\nINNER JOIN dbo.tblMember tm ON tm.id = t.tblmemberId\nINNER JOIN dbo.AccountInfo a ON tm.accountInfoId = a.ID\nINNER JOIN dbo.Subscription sub ON sub.accountInfoID = a.ID\nINNER JOIN dbo.AccountsToDelete atd ON a.ID = atd.AccountId\n/**WHERE \n    sub.OrganizationTypeId <> 2\n    OR (\n        sub.OrganizationTypeId = 2\n        AND a.ID NOT IN (23382)\n        AND sub.SubscriptionStatusID <> 1\n        AND sub.dateSubscriptionStatusChanged <= DATEADD(MONTH, -6, GETDATE())\n    );\n**/",
										"type": "Expression"
									}
								}
							],
							"scriptBlockExecutionTimeout": "02:00:00"
						}
					}
				],
				"policy": {
					"elapsedTimeMetric": {}
				},
				"annotations": [],
				"lastPublishTime": "2026-04-30T15:36:29Z"
			},
			"dependsOn": []
		},
		{
			"name": "[concat(parameters('factoryName'), '/Delete_hcStaffMemberLocation')]",
			"type": "Microsoft.DataFactory/factories/pipelines",
			"apiVersion": "2018-06-01",
			"properties": {
				"activities": [
					{
						"name": "Script1",
						"type": "Script",
						"dependsOn": [],
						"policy": {
							"timeout": "0.12:00:00",
							"retry": 0,
							"retryIntervalInSeconds": 30,
							"secureOutput": false,
							"secureInput": false
						},
						"userProperties": [],
						"linkedServiceName": {
							"referenceName": "BHDataArchiveDev",
							"type": "LinkedServiceReference"
						},
						"typeProperties": {
							"scripts": [
								{
									"type": "Query",
									"text": {
										"value": "DELETE t\nFROM dbo.hcStaffMemberLocation t\nINNER JOIN dbo.tblMember tm ON tm.id = t.tblmemberId\nINNER JOIN dbo.AccountInfo a ON tm.accountInfoId = a.ID\nINNER JOIN dbo.Subscription sub ON sub.accountInfoID = a.ID\nINNER JOIN dbo.AccountsToDelete atd ON a.ID = atd.AccountId\n/**WHERE \n    sub.OrganizationTypeId <> 2\n    OR (\n        sub.OrganizationTypeId = 2\n        AND a.ID NOT IN (23382)  -- Exclude test account\n        AND sub.SubscriptionStatusID <> 1\n        AND sub.dateSubscriptionStatusChanged <= DATEADD(MONTH, -6, GETDATE())\n    );\n**/",
										"type": "Expression"
									}
								}
							],
							"scriptBlockExecutionTimeout": "02:00:00"
						}
					}
				],
				"policy": {
					"elapsedTimeMetric": {}
				},
				"annotations": [],
				"lastPublishTime": "2026-04-30T15:36:13Z"
			},
			"dependsOn": []
		},
		{
			"name": "[concat(parameters('factoryName'), '/Delete_hcStaffMemberPayroll')]",
			"type": "Microsoft.DataFactory/factories/pipelines",
			"apiVersion": "2018-06-01",
			"properties": {
				"activities": [
					{
						"name": "Script1",
						"type": "Script",
						"dependsOn": [],
						"policy": {
							"timeout": "0.12:00:00",
							"retry": 0,
							"retryIntervalInSeconds": 30,
							"secureOutput": false,
							"secureInput": false
						},
						"userProperties": [],
						"linkedServiceName": {
							"referenceName": "BHDataArchiveDev",
							"type": "LinkedServiceReference"
						},
						"typeProperties": {
							"scripts": [
								{
									"type": "Query",
									"text": {
										"value": "DELETE t\nFROM dbo.hcStaffMemberPayroll t\nINNER JOIN dbo.tblMember tm ON tm.id = t.tblmemberId\nINNER JOIN dbo.AccountInfo a ON tm.accountInfoId = a.ID\nINNER JOIN dbo.Subscription sub ON sub.accountInfoID = a.ID\nINNER JOIN dbo.AccountsToDelete atd ON a.ID = atd.AccountId\n/**WHERE \n    sub.OrganizationTypeId <> 2\n    OR (\n        sub.OrganizationTypeId = 2\n        AND a.ID NOT IN (23382)\n        AND sub.SubscriptionStatusID <> 1\n        AND sub.dateSubscriptionStatusChanged <= DATEADD(MONTH, -6, GETDATE())\n    );\n**/",
										"type": "Expression"
									}
								}
							],
							"scriptBlockExecutionTimeout": "02:00:00"
						}
					}
				],
				"policy": {
					"elapsedTimeMetric": {}
				},
				"annotations": [],
				"lastPublishTime": "2026-04-30T15:36:19Z"
			},
			"dependsOn": []
		},
		{
			"name": "[concat(parameters('factoryName'), '/Delete_hcStaffMileage')]",
			"type": "Microsoft.DataFactory/factories/pipelines",
			"apiVersion": "2018-06-01",
			"properties": {
				"activities": [
					{
						"name": "Script1",
						"type": "Script",
						"dependsOn": [],
						"policy": {
							"timeout": "0.12:00:00",
							"retry": 0,
							"retryIntervalInSeconds": 30,
							"secureOutput": false,
							"secureInput": false
						},
						"userProperties": [],
						"linkedServiceName": {
							"referenceName": "BHDataArchiveDev",
							"type": "LinkedServiceReference"
						},
						"typeProperties": {
							"scripts": [
								{
									"type": "Query",
									"text": {
										"value": "DELETE t\nFROM dbo.hcStaffMileage t\nINNER JOIN dbo.AccountInfo a ON t.accountInfoId = a.ID\nINNER JOIN dbo.Subscription sub ON sub.accountInfoID = a.ID\nINNER JOIN dbo.AccountsToDelete atd ON a.ID = atd.AccountId\n/**WHERE \n    sub.OrganizationTypeId <> 2\n    OR (\n        sub.OrganizationTypeId = 2\n        AND a.ID NOT IN (23382)\n        AND sub.SubscriptionStatusID <> 1\n        AND sub.dateSubscriptionStatusChanged <= DATEADD(MONTH, -6, GETDATE())\n    );\n**/",
										"type": "Expression"
									}
								}
							],
							"scriptBlockExecutionTimeout": "02:00:00"
						}
					}
				],
				"policy": {
					"elapsedTimeMetric": {}
				},
				"annotations": [],
				"lastPublishTime": "2026-04-30T15:36:29Z"
			},
			"dependsOn": []
		},
		{
			"name": "[concat(parameters('factoryName'), '/Delete_hcStaffPaycodes')]",
			"type": "Microsoft.DataFactory/factories/pipelines",
			"apiVersion": "2018-06-01",
			"properties": {
				"activities": [
					{
						"name": "Script1",
						"type": "Script",
						"dependsOn": [],
						"policy": {
							"timeout": "0.12:00:00",
							"retry": 0,
							"retryIntervalInSeconds": 30,
							"secureOutput": false,
							"secureInput": false
						},
						"userProperties": [],
						"linkedServiceName": {
							"referenceName": "BHDataArchiveDev",
							"type": "LinkedServiceReference"
						},
						"typeProperties": {
							"scripts": [
								{
									"type": "Query",
									"text": {
										"value": "DELETE t\nFROM dbo.hcStaffPaycodes t\nINNER JOIN dbo.AccountInfo a ON t.accountInfoId = a.ID\nINNER JOIN dbo.Subscription sub ON sub.accountInfoID = a.ID\nINNER JOIN dbo.AccountsToDelete atd ON a.ID = atd.AccountId\n/**WHERE \n    sub.OrganizationTypeId <> 2\n    OR (\n        sub.OrganizationTypeId = 2\n        AND a.ID NOT IN (23382)\n        AND sub.SubscriptionStatusID <> 1\n        AND sub.dateSubscriptionStatusChanged <= DATEADD(MONTH, -6, GETDATE())\n    );\n**/",
										"type": "Expression"
									}
								}
							],
							"scriptBlockExecutionTimeout": "02:00:00"
						}
					}
				],
				"policy": {
					"elapsedTimeMetric": {}
				},
				"annotations": [],
				"lastPublishTime": "2026-04-30T15:36:30Z"
			},
			"dependsOn": []
		},
		{
			"name": "[concat(parameters('factoryName'), '/Delete_hcStaffService')]",
			"type": "Microsoft.DataFactory/factories/pipelines",
			"apiVersion": "2018-06-01",
			"properties": {
				"activities": [
					{
						"name": "Script1",
						"type": "Script",
						"dependsOn": [],
						"policy": {
							"timeout": "0.12:00:00",
							"retry": 0,
							"retryIntervalInSeconds": 30,
							"secureOutput": false,
							"secureInput": false
						},
						"userProperties": [],
						"linkedServiceName": {
							"referenceName": "BHDataArchiveDev",
							"type": "LinkedServiceReference"
						},
						"typeProperties": {
							"scripts": [
								{
									"type": "Query",
									"text": {
										"value": "DELETE t\nFROM dbo.hcStaffService t\nINNER JOIN dbo.tblMember tm ON tm.id = t.staffmemberId\nINNER JOIN dbo.AccountInfo a ON tm.accountInfoId = a.ID\nINNER JOIN dbo.Subscription sub ON sub.accountInfoID = a.ID\nINNER JOIN dbo.AccountsToDelete atd ON a.ID = atd.AccountId\nwhere t.id NOT IN (8181, 9533);\n/**WHERE \n    (\n        sub.OrganizationTypeId <> 2\n        OR (\n            sub.OrganizationTypeId = 2\n            AND a.ID NOT IN (23382)\n            AND sub.SubscriptionStatusID <> 1\n            AND sub.dateSubscriptionStatusChanged <= DATEADD(MONTH, -6, GETDATE())\n        )\n    )\n    AND t.id NOT IN (8181, 9533); -- Exclude bad records\n**/",
										"type": "Expression"
									}
								}
							],
							"scriptBlockExecutionTimeout": "02:00:00"
						}
					}
				],
				"policy": {
					"elapsedTimeMetric": {}
				},
				"annotations": [],
				"lastPublishTime": "2026-04-30T15:36:15Z"
			},
			"dependsOn": []
		},
		{
			"name": "[concat(parameters('factoryName'), '/Delete_hcStaffServiceFunder')]",
			"type": "Microsoft.DataFactory/factories/pipelines",
			"apiVersion": "2018-06-01",
			"properties": {
				"activities": [
					{
						"name": "Script1",
						"type": "Script",
						"dependsOn": [],
						"policy": {
							"timeout": "0.12:00:00",
							"retry": 0,
							"retryIntervalInSeconds": 30,
							"secureOutput": false,
							"secureInput": false
						},
						"userProperties": [],
						"linkedServiceName": {
							"referenceName": "BHDataArchiveDev",
							"type": "LinkedServiceReference"
						},
						"typeProperties": {
							"scripts": [
								{
									"type": "Query",
									"text": {
										"value": "DELETE t\nFROM dbo.hcStaffServiceFunder t\nINNER JOIN dbo.hcStaffService hs ON t.hcstaffserviceid = hs.id\nINNER JOIN dbo.tblMember tm ON tm.id = hs.staffmemberId\nINNER JOIN dbo.AccountInfo a ON tm.accountInfoId = a.ID\nINNER JOIN dbo.Subscription sub ON sub.accountInfoID = a.ID\nINNER JOIN dbo.AccountsToDelete atd ON a.ID = atd.AccountId\n/**WHERE \n    sub.OrganizationTypeId <> 2\n    OR (\n        sub.OrganizationTypeId = 2\n        AND a.ID NOT IN (23382)\n        AND sub.SubscriptionStatusID <> 1\n        AND sub.dateSubscriptionStatusChanged <= DATEADD(MONTH, -6, GETDATE())\n    );\n**/",
										"type": "Expression"
									}
								}
							],
							"scriptBlockExecutionTimeout": "02:00:00"
						}
					}
				],
				"policy": {
					"elapsedTimeMetric": {}
				},
				"annotations": [],
				"lastPublishTime": "2026-04-30T15:36:23Z"
			},
			"dependsOn": []
		},
		{
			"name": "[concat(parameters('factoryName'), '/Delete_hcStaffStatus')]",
			"type": "Microsoft.DataFactory/factories/pipelines",
			"apiVersion": "2018-06-01",
			"properties": {
				"activities": [
					{
						"name": "Script1",
						"type": "Script",
						"dependsOn": [],
						"policy": {
							"timeout": "0.12:00:00",
							"retry": 0,
							"retryIntervalInSeconds": 30,
							"secureOutput": false,
							"secureInput": false
						},
						"userProperties": [],
						"linkedServiceName": {
							"referenceName": "BHDataArchiveDev",
							"type": "LinkedServiceReference"
						},
						"typeProperties": {
							"scripts": [
								{
									"type": "Query",
									"text": {
										"value": "DELETE t\nFROM dbo.hcStaffStatus t\nINNER JOIN dbo.AccountInfo a ON t.accountInfoId = a.ID\nINNER JOIN dbo.Subscription sub ON sub.accountInfoID = a.ID\nINNER JOIN dbo.AccountsToDelete atd ON a.ID = atd.AccountId\n/**WHERE \n    sub.OrganizationTypeId <> 2\n    OR (\n        sub.OrganizationTypeId = 2\n        AND a.ID NOT IN (23382)\n        AND sub.SubscriptionStatusID <> 1\n        AND sub.dateSubscriptionStatusChanged <= DATEADD(MONTH, -6, GETDATE())\n    );\n**/",
										"type": "Expression"
									}
								}
							],
							"scriptBlockExecutionTimeout": "02:00:00"
						}
					}
				],
				"policy": {
					"elapsedTimeMetric": {}
				},
				"annotations": [],
				"lastPublishTime": "2026-04-30T15:36:15Z"
			},
			"dependsOn": []
		},
		{
			"name": "[concat(parameters('factoryName'), '/Delete_hcStaffTitle')]",
			"type": "Microsoft.DataFactory/factories/pipelines",
			"apiVersion": "2018-06-01",
			"properties": {
				"activities": [
					{
						"name": "Script1",
						"type": "Script",
						"dependsOn": [],
						"policy": {
							"timeout": "0.12:00:00",
							"retry": 0,
							"retryIntervalInSeconds": 30,
							"secureOutput": false,
							"secureInput": false
						},
						"userProperties": [],
						"linkedServiceName": {
							"referenceName": "BHDataArchiveDev",
							"type": "LinkedServiceReference"
						},
						"typeProperties": {
							"scripts": [
								{
									"type": "Query",
									"text": {
										"value": "DELETE t\nFROM dbo.hcStaffTitle t\nINNER JOIN dbo.AccountInfo a ON t.accountInfoId = a.ID\nINNER JOIN dbo.Subscription sub ON sub.accountInfoID = a.ID\nINNER JOIN dbo.AccountsToDelete atd ON a.ID = atd.AccountId\n/**WHERE \n    sub.OrganizationTypeId <> 2\n    OR (\n        sub.OrganizationTypeId = 2\n        AND a.ID NOT IN (23382)\n        AND sub.SubscriptionStatusID <> 1\n        AND sub.dateSubscriptionStatusChanged <= DATEADD(MONTH, -6, GETDATE())\n    );\n**/",
										"type": "Expression"
									}
								}
							],
							"scriptBlockExecutionTimeout": "02:00:00"
						}
					}
				],
				"policy": {
					"elapsedTimeMetric": {}
				},
				"annotations": [],
				"lastPublishTime": "2026-04-30T15:36:23Z"
			},
			"dependsOn": []
		},
		{
			"name": "[concat(parameters('factoryName'), '/Delete_hcTasks')]",
			"type": "Microsoft.DataFactory/factories/pipelines",
			"apiVersion": "2018-06-01",
			"properties": {
				"activities": [
					{
						"name": "Script1",
						"type": "Script",
						"dependsOn": [],
						"policy": {
							"timeout": "0.12:00:00",
							"retry": 0,
							"retryIntervalInSeconds": 30,
							"secureOutput": false,
							"secureInput": false
						},
						"userProperties": [],
						"linkedServiceName": {
							"referenceName": "BHDataArchiveDev",
							"type": "LinkedServiceReference"
						},
						"typeProperties": {
							"scripts": [
								{
									"type": "Query",
									"text": {
										"value": "DELETE t\nFROM dbo.hcTasks t\nINNER JOIN dbo.ChildProfile cp ON t.Referenceid = cp.id\nINNER JOIN dbo.AccountInfo a ON cp.accountInfoId = a.ID\nINNER JOIN dbo.Subscription sub ON sub.accountInfoID = a.ID\nINNER JOIN dbo.AccountsToDelete atd ON a.ID = atd.AccountId\n/**WHERE \n    sub.OrganizationTypeId <> 2\n    OR (\n        sub.OrganizationTypeId = 2\n        AND a.ID NOT IN (23382)\n        AND sub.SubscriptionStatusID <> 1\n        AND sub.dateSubscriptionStatusChanged <= DATEADD(MONTH, -6, GETDATE())\n    );\n***/",
										"type": "Expression"
									}
								}
							],
							"scriptBlockExecutionTimeout": "02:00:00"
						}
					}
				],
				"policy": {
					"elapsedTimeMetric": {}
				},
				"annotations": [],
				"lastPublishTime": "2026-04-30T15:36:29Z"
			},
			"dependsOn": []
		},
		{
			"name": "[concat(parameters('factoryName'), '/Delete_hcTransaction')]",
			"type": "Microsoft.DataFactory/factories/pipelines",
			"apiVersion": "2018-06-01",
			"properties": {
				"activities": [
					{
						"name": "Script1",
						"type": "Script",
						"dependsOn": [],
						"policy": {
							"timeout": "0.12:00:00",
							"retry": 0,
							"retryIntervalInSeconds": 30,
							"secureOutput": false,
							"secureInput": false
						},
						"userProperties": [],
						"linkedServiceName": {
							"referenceName": "BHDataArchiveDev",
							"type": "LinkedServiceReference"
						},
						"typeProperties": {
							"scripts": [
								{
									"type": "Query",
									"text": {
										"value": "DELETE t\nFROM dbo.hcTransaction t\nWHERE t.referenceId IN (\n    SELECT DISTINCT ha.AppointmentId\n    FROM dbo.hcAppointments ha\n    INNER JOIN dbo.ChildProfile cp ON ha.clientId = cp.id\n    INNER JOIN dbo.AccountInfo a ON cp.accountInfoId = a.ID\n    INNER JOIN dbo.Subscription sub ON sub.accountInfoID = a.ID\n    INNER JOIN dbo.AccountsToDelete atd ON a.ID = atd.AccountId\n)\nAND t.hcTransactionTypeId != 0;\n\n",
										"type": "Expression"
									}
								}
							],
							"scriptBlockExecutionTimeout": "02:00:00"
						}
					}
				],
				"policy": {
					"elapsedTimeMetric": {}
				},
				"annotations": [],
				"lastPublishTime": "2026-04-30T15:36:13Z"
			},
			"dependsOn": []
		},
		{
			"name": "[concat(parameters('factoryName'), '/Delete_hcWorkflowHistory')]",
			"type": "Microsoft.DataFactory/factories/pipelines",
			"apiVersion": "2018-06-01",
			"properties": {
				"activities": [
					{
						"name": "Script1",
						"type": "Script",
						"dependsOn": [],
						"policy": {
							"timeout": "0.12:00:00",
							"retry": 0,
							"retryIntervalInSeconds": 30,
							"secureOutput": false,
							"secureInput": false
						},
						"userProperties": [],
						"linkedServiceName": {
							"referenceName": "BHDataArchiveDev",
							"type": "LinkedServiceReference"
						},
						"typeProperties": {
							"scripts": [
								{
									"type": "Query",
									"text": {
										"value": "DELETE t\nFROM dbo.hcWorkflowHistory t\nINNER JOIN dbo.hcAppointments ha ON t.referenceId = ha.AppointmentId\nINNER JOIN dbo.ChildProfile cp ON ha.clientId = cp.id\nINNER JOIN dbo.AccountInfo a ON cp.accountInfoId = a.ID\nINNER JOIN dbo.Subscription sub ON sub.accountInfoID = a.ID\nINNER JOIN dbo.AccountsToDelete atd ON a.ID = atd.AccountId\n/**WHERE \n    sub.OrganizationTypeId <> 2\n    OR (\n        sub.OrganizationTypeId = 2\n        AND a.ID NOT IN (23382)\n        AND sub.SubscriptionStatusID <> 1\n        AND sub.dateSubscriptionStatusChanged <= DATEADD(MONTH, -6, GETDATE())\n    );\n**/",
										"type": "Expression"
									}
								}
							],
							"scriptBlockExecutionTimeout": "02:00:00"
						}
					}
				],
				"policy": {
					"elapsedTimeMetric": {}
				},
				"annotations": [],
				"lastPublishTime": "2026-04-30T15:36:14Z"
			},
			"dependsOn": []
		},
		{
			"name": "[concat(parameters('factoryName'), '/Delete_hcemployeetype')]",
			"type": "Microsoft.DataFactory/factories/pipelines",
			"apiVersion": "2018-06-01",
			"properties": {
				"activities": [
					{
						"name": "Script1",
						"type": "Script",
						"dependsOn": [],
						"policy": {
							"timeout": "0.12:00:00",
							"retry": 0,
							"retryIntervalInSeconds": 30,
							"secureOutput": false,
							"secureInput": false
						},
						"userProperties": [],
						"linkedServiceName": {
							"referenceName": "BHDataArchiveDev",
							"type": "LinkedServiceReference"
						},
						"typeProperties": {
							"scripts": [
								{
									"type": "Query",
									"text": {
										"value": "DELETE t\nFROM dbo.hcEmployeeType t\nINNER JOIN dbo.AccountInfo a ON t.accountInfoId = a.ID\nINNER JOIN dbo.Subscription sub ON sub.accountInfoID = a.ID\nINNER JOIN dbo.AccountsToDelete atd ON a.ID = atd.AccountId\n/**WHERE \n    (\n        sub.OrganizationTypeId <> 2\n        OR (\n            sub.OrganizationTypeId = 2\n            AND a.ID NOT IN (23382)\n            AND sub.SubscriptionStatusID <> 1\n            AND sub.dateSubscriptionStatusChanged <= DATEADD(MONTH, -6, GETDATE())\n        )\n    );\n**/",
										"type": "Expression"
									}
								}
							],
							"scriptBlockExecutionTimeout": "02:00:00"
						}
					}
				],
				"policy": {
					"elapsedTimeMetric": {}
				},
				"annotations": [],
				"lastPublishTime": "2026-04-30T15:36:13Z"
			},
			"dependsOn": []
		},
		{
			"name": "[concat(parameters('factoryName'), '/Delete_hollowAccountInfoSubscriber')]",
			"type": "Microsoft.DataFactory/factories/pipelines",
			"apiVersion": "2018-06-01",
			"properties": {
				"activities": [
					{
						"name": "Script1",
						"type": "Script",
						"dependsOn": [],
						"policy": {
							"timeout": "0.12:00:00",
							"retry": 0,
							"retryIntervalInSeconds": 30,
							"secureOutput": false,
							"secureInput": false
						},
						"userProperties": [],
						"linkedServiceName": {
							"referenceName": "BHDataArchiveDev",
							"type": "LinkedServiceReference"
						},
						"typeProperties": {
							"scripts": [
								{
									"type": "Query",
									"text": {
										"value": "DELETE t\nFROM dbo.hollowAccountInfoSubscriber t\nINNER JOIN dbo.AccountInfo a ON t.accountInfoId = a.ID\nINNER JOIN dbo.Subscription sub ON sub.accountInfoID = a.ID\nINNER JOIN dbo.AccountsToDelete atd ON a.ID = atd.AccountId\nWHERE \n    sub.OrganizationTypeId <> 2\n    OR (\n        sub.OrganizationTypeId = 2\n        AND a.ID NOT IN (23382)\n        AND sub.SubscriptionStatusID <> 1\n        AND sub.dateSubscriptionStatusChanged <= DATEADD(MONTH, -6, GETDATE())\n    );\n",
										"type": "Expression"
									}
								}
							],
							"scriptBlockExecutionTimeout": "02:00:00"
						}
					}
				],
				"policy": {
					"elapsedTimeMetric": {}
				},
				"annotations": [],
				"lastPublishTime": "2026-04-30T15:36:14Z"
			},
			"dependsOn": []
		},
		{
			"name": "[concat(parameters('factoryName'), '/Delete_hollowAccountLeaderRole6')]",
			"type": "Microsoft.DataFactory/factories/pipelines",
			"apiVersion": "2018-06-01",
			"properties": {
				"activities": [
					{
						"name": "Script1",
						"type": "Script",
						"dependsOn": [],
						"policy": {
							"timeout": "0.12:00:00",
							"retry": 0,
							"retryIntervalInSeconds": 30,
							"secureOutput": false,
							"secureInput": false
						},
						"userProperties": [],
						"linkedServiceName": {
							"referenceName": "BHDataArchiveDev",
							"type": "LinkedServiceReference"
						},
						"typeProperties": {
							"scripts": [
								{
									"type": "Query",
									"text": {
										"value": "DELETE t\nFROM dbo.hollowAccountLeaderRole6 t\nINNER JOIN dbo.AccountInfo a ON t.accountInfoId = a.ID\nINNER JOIN dbo.Subscription sub ON sub.accountInfoID = a.ID\nINNER JOIN dbo.AccountsToDelete atd ON a.ID = atd.AccountId\nWHERE \n    sub.OrganizationTypeId <> 2\n    OR (\n        sub.OrganizationTypeId = 2\n        AND a.ID NOT IN (23382)\n        AND sub.SubscriptionStatusID <> 1\n        AND sub.dateSubscriptionStatusChanged <= DATEADD(MONTH, -6, GETDATE())\n    );\n",
										"type": "Expression"
									}
								}
							],
							"scriptBlockExecutionTimeout": "02:00:00"
						}
					}
				],
				"policy": {
					"elapsedTimeMetric": {}
				},
				"annotations": [],
				"lastPublishTime": "2026-04-30T15:36:24Z"
			},
			"dependsOn": []
		}
	]
}